ooputils/__init__.py
ooputils/setup.py
ooputils-0.1.0.dist-info/METADATA
ooputils-0.1.0.dist-info/WHEEL
ooputils-0.1.0.dist-info/top_level.txt
ooputils-0.1.0.dist-info/RECORD
