Metadata-Version: 2.2
Name: ooputils
Version: 0.1.0
Summary: Library for OOP utilities
Author: Rafael da Rocha Ferreira
Author-email: programadorlhama@gmail.com
Classifier: Programming Language :: Python :: 3
Classifier: License :: OSI Approved :: MIT License
Classifier: Operating System :: OS Independent
Requires-Python: >=3.6
Dynamic: author
Dynamic: author-email
Dynamic: classifier
Dynamic: requires-python
Dynamic: summary
